assets/mcp-server-toolhouse-banner.svg
src/mcp_server_toolhouse/__init__.py
src/mcp_server_toolhouse/server.py
mseep_mcp_server_toolhouse-0.2.0.dist-info/METADATA
mseep_mcp_server_toolhouse-0.2.0.dist-info/WHEEL
mseep_mcp_server_toolhouse-0.2.0.dist-info/entry_points.txt
mseep_mcp_server_toolhouse-0.2.0.dist-info/licenses/LICENSE.md
mseep_mcp_server_toolhouse-0.2.0.dist-info/RECORD
