Metadata-Version: 2.4
Name: mseep-mcp-server-toolhouse
Version: 0.2.0
Summary: All the high-quality toolhouse tools in one place, accessible as one MCP server
Author-email: orliesaurus <orlando@toolhouse.ai>
License-File: LICENSE.md
Requires-Python: >=3.13
Requires-Dist: httpx>=0.28.1
Requires-Dist: mcp>=1.2
